opet/__init__.py
opet/api.py
opet/exceptions.py
opet/main.py
opet/utils.py
opet/server/__init__.py
opet/server/app.py
opet/server/run.py
opet/server/controllers/__init__.py
opet/server/controllers/fuel.py
opet/server/models/__init__.py
opet/server/models/fuel.py
opet/server/providers/__init__.py
opet/server/providers/opet.py
opet-0.1.3.dist-info/licenses/LICENSE
tests/__init__.py
tests/test_api.py
tests/test_main.py
tests/test_utils.py
opet-0.1.3.dist-info/METADATA
opet-0.1.3.dist-info/WHEEL
opet-0.1.3.dist-info/entry_points.txt
opet-0.1.3.dist-info/top_level.txt
opet-0.1.3.dist-info/RECORD
