Metadata-Version: 2.4
Name: opet
Version: 0.1.3
Summary: ('A Python package that allows you to view fuel', 'prices in Turkey based on cities.')
Home-page: https://github.com/sinanerdinc/opet
Author: Sinan Erdinc
Author-email: hello@sinanerdinc.com
Classifier: Programming Language :: Python :: 3
Classifier: License :: OSI Approved :: MIT License
Classifier: Operating System :: OS Independent
Requires-Python: >=3.0
License-File: LICENSE
Requires-Dist: requests==2.32.1
Requires-Dist: click==8.0.0
Requires-Dist: fastapi==0.109.2
Requires-Dist: uvicorn==0.27.1
Requires-Dist: pydantic==2.6.1
Requires-Dist: typing-extensions==4.9.0
Dynamic: author
Dynamic: author-email
Dynamic: classifier
Dynamic: description
Dynamic: description-content-type
Dynamic: home-page
Dynamic: license-file
Dynamic: requires-dist
Dynamic: requires-python
Dynamic: summary
